mytoolit/__init__.py
mytoolit/can/__init__.py
mytoolit/can/adc.py
mytoolit/can/calibration.py
mytoolit/can/command.py
mytoolit/can/error.py
mytoolit/can/identifier.py
mytoolit/can/message.py
mytoolit/can/network.py
mytoolit/can/node.py
mytoolit/can/status.py
mytoolit/can/streaming.py
mytoolit/cmdline/__init__.py
mytoolit/cmdline/commander.py
mytoolit/cmdline/parse.py
mytoolit/config/__init__.py
mytoolit/config/config.py
mytoolit/config/config.yaml
mytoolit/config/user.yaml
mytoolit/eeprom/__init__.py
mytoolit/eeprom/status.py
mytoolit/examples/read_data.py
mytoolit/examples/sth_name.py
mytoolit/examples/store_data.py
mytoolit/experiments/RF_tests.py
mytoolit/experiments/dataloss.py
mytoolit/experiments/new.py
mytoolit/experiments/old.py
mytoolit/experiments/perf.py
mytoolit/measurement/__init__.py
mytoolit/measurement/acceleration.py
mytoolit/measurement/constants.py
mytoolit/measurement/sensor.py
mytoolit/measurement/storage.py
mytoolit/measurement/voltage.py
mytoolit/old/MyToolItCommands.py
mytoolit/old/MyToolItNetworkNumbers.py
mytoolit/old/MyToolItSth.py
mytoolit/old/MyToolItStu.py
mytoolit/old/Plotter.py
mytoolit/old/SthLimits.py
mytoolit/old/StuLimits.py
mytoolit/old/__init__.py
mytoolit/old/cli.py
mytoolit/old/network.py
mytoolit/old/ui.py
mytoolit/old/test/HardwareSth.py
mytoolit/old/test/MyToolItTestSth.py
mytoolit/old/test/MyToolItTestSthManually.py
mytoolit/old/test/MyToolItTestStu.py
mytoolit/old/test/MyToolItTestStuManually.py
mytoolit/old/test/__init__.py
mytoolit/old/test/testSignal.py
mytoolit/report/MyTooliT.pdf
mytoolit/report/__init__.py
mytoolit/report/forms.py
mytoolit/report/pdf.py
mytoolit/report/report.py
mytoolit/report/style.py
mytoolit/scripts/eeprom.py
mytoolit/scripts/icon.py
mytoolit/scripts/mac.py
mytoolit/scripts/name.py
mytoolit/test/__init__.py
mytoolit/test/production/__init__.py
mytoolit/test/production/node.py
mytoolit/test/production/sensor_node.py
mytoolit/test/production/smh.py
mytoolit/test/production/sth.py
icoc-2.1.0.dist-info/METADATA
icoc-2.1.0.dist-info/WHEEL
icoc-2.1.0.dist-info/entry_points.txt
icoc-2.1.0.dist-info/top_level.txt
icoc-2.1.0.dist-info/RECORD
