Metadata-Version: 2.2
Name: icoc
Version: 2.1.0
Summary: Control and test software for sensory tool holders (STH), sensor milling heads (SMH) and stationary transceiver units (STU)
Author-email: Clemens Burgstaller <burgstaller@ift.at>, Christoph Mayer <mayer@ift.at>, René Schwaiger <rene.schwaiger@ift.at>
Project-URL: Documentation, https://mytoolit.github.io/ICOc/
Project-URL: Source, https://github.com/mytoolit/ICOc/
Keywords: smart-tool,smh,stu,sth,tool-holder
Classifier: Development Status :: 3 - Alpha
Classifier: License :: Other/Proprietary License
Classifier: Natural Language :: English
Classifier: Operating System :: MacOS
Classifier: Operating System :: POSIX :: Linux
Classifier: Operating System :: Microsoft :: Windows :: Windows 10
Classifier: Programming Language :: Python
Requires-Python: >=3.10
Requires-Dist: bidict<2,>=0.22.1
Requires-Dist: dynaconf<4,>=3.1.12
Requires-Dist: matplotlib<4,>=3.7.1
Requires-Dist: netaddr<2,>=0.8.0
Requires-Dist: pdfrw<2,>=0.4
Requires-Dist: platformdirs<5,>=3.5.0
Requires-Dist: python-can[pcan]<5,>=4
Requires-Dist: pywin32>=306; os_name == "nt"
Requires-Dist: reportlab<5,>=4.0.4
Requires-Dist: tables<4,>=3.10.1
Requires-Dist: tqdm<5,>=4.65
Requires-Dist: typing_extensions>=4.7.1
Requires-Dist: semantic_version<3,>=2.10
Requires-Dist: windows-curses<3,>=2.3.3; os_name == "nt"
Provides-Extra: dev
Requires-Dist: Flake8-pyproject>=1.2.3; extra == "dev"
Requires-Dist: mypy; extra == "dev"
Requires-Dist: pylint>=3.3.1; extra == "dev"
Requires-Dist: toml; extra == "dev"
Provides-Extra: test
Requires-Dist: icolyzer>=1.5.0; extra == "test"
Requires-Dist: prysk[pytest-plugin]>=0.13.1; extra == "test"
Requires-Dist: maisie-sphinx-theme>=0.1.2; extra == "test"
